cli_subcommand_tools/__init__.py
cli_subcommand_tools/tools.py
cli_subcommand_tools-0.1.0.dist-info/METADATA
cli_subcommand_tools-0.1.0.dist-info/WHEEL
cli_subcommand_tools-0.1.0.dist-info/top_level.txt
cli_subcommand_tools-0.1.0.dist-info/RECORD
