Metadata-Version: 2.1
Name: cli-subcommand-tools
Version: 0.1.0
Summary: A small set of utilities for making subcommand-based CLI interfaces
Home-page: https://github.com/j-sloan/cli_subcommand_tools
Author: jonny sloan
License: GPL3
Platform: UNKNOWN
